kraw/__init__.py
kraw/connection.py
kraw/dummies.py
kraw/reddit.py
kraw-0.3.6.dist-info/LICENSE
kraw-0.3.6.dist-info/METADATA
kraw-0.3.6.dist-info/WHEEL
kraw-0.3.6.dist-info/RECORD
