Metadata-Version: 2.1
Name: kraw
Version: 0.3.6
Summary: Reddit API wrapper for Knew Karma
Home-page: https://github.com/knewkarma-io/kraw
License: GPL-3.0+
Author: Richard Mwewa
Author-email: rly0nheart@duck.com
Requires-Python: >=3.10,<4.0
Classifier: License :: OSI Approved :: GNU General Public License v3 or later (GPLv3+)
Classifier: Programming Language :: Python :: 3
Classifier: Programming Language :: Python :: 3.10
Classifier: Programming Language :: Python :: 3.11
Classifier: Programming Language :: Python :: 3.12
Classifier: Programming Language :: Python :: 3.13
Requires-Dist: aiohttp (>=3.10.10,<4.0.0)
Requires-Dist: karmakaze (>=3.0.1,<4.0.0)
